[{"Name":"АгроСоюз ООО","FullName":"ООО \"АгроСоюз\"","NameBash":"Регионсбыт 116","NameLuk":""},{"Name":"Александровская школа Кез","FullName":"МБОУ \"АЛЕКСАНДРОВСКАЯ СОШ\"","NameBash":"Регионсбыт 99","NameLuk":"Александровская СОШ"},{"Name":"Алнашская Администрация","FullName":"Администрация муниципального образования \"Алнашский район\"","NameBash":"Регионсбыт 7","NameLuk":""},{"Name":"Алнашская ЦРБ","FullName":"БУЗ УР \"АЛНАШСКАЯ РБ МЗ УР\"","NameBash":"Регионсбыт 111","NameLuk":""},{"Name":"Бабинские колбасы БК ","FullName":"ООО \"Бабинские колбасы\" ","NameBash":"Регионсбыт 89","NameLuk":""},{"Name":"Балезинская Администрация","FullName":"АДМИНИСТРАЦИЯ  БАЛЕЗИНСКОГО РАЙОНА","NameBash":"Регионсбыт 143","NameLuk":"Регионсбыт АБал рай"},{"Name":"Балезинская ЦРБ","FullName":"БУЗ УР \"БАЛЕЗИНСКАЯ РБ МЗ УР\"","NameBash":"Регионсбыт 132","NameLuk":""},{"Name":"Баскаков Алексей Вячеславович ИП","FullName":"ИП Баскаков Алексей Вячеславович","NameBash":"Регионсбыт 144","NameLuk":""},{"Name":"Бачкеевская школа Игра","FullName":"МБОУ Бачкеевская НОШ","NameBash":"Регионсбыт 200","NameLuk":""},{"Name":"БДД УР КУ УР","FullName":"КУ УР \"БДД УР\"","NameBash":"Регионсбыт 177","NameLuk":""},{"Name":"Больше-Пургинская школа Игра","FullName":"МБОУ БОЛЬШЕ - ПУРГИНСКАЯ СОШ","NameBash":"Регионсбыт 54","NameLuk":""},{"Name":"БОЛЬШЕОШВОРЦИНСКАЯ СОШ Якшур-Бод","FullName":"МБОУ БОЛЬШЕОШВОРЦИНСКАЯ СОШ","NameBash":"Регионсбыт 67","NameLuk":""},{"Name":"Большесибинская школа Можга","FullName":"МБОУ \"БОЛЬШЕСИБИНСКАЯ ООШ\"","NameBash":"Регионсбыт 65","NameLuk":""},{"Name":"Быгинская школа Шаркан","FullName":"МБОУ БЫГИНСКАЯ СОШ","NameBash":"","NameLuk":"МБОУ Быгинская СОШ"},{"Name":"Вавожская ЦРБ","FullName":"БУЗ УР \"ВАВОЖСКАЯ РБ МЗ УР\"","NameBash":"","NameLuk":"Регионсбыт ВавЦРБ"},{"Name":"Верхне-Волж УГМС Удм ф-л","FullName":"Удмуртский ЦГМС - филиал ФГБУ \"Верхне-Волжское УГМС\"","NameBash":"Регионсбыт 8","NameLuk":"Регионсбыт ГИДРОМ"},{"Name":"Верхнеюринская школа Можга","FullName":"МБОУ \"Верхнеюринская основная ООШ\"","NameBash":"Регионсбыт 57","NameLuk":""},{"Name":"Вневедом ФГКУ УВО при МВД","FullName":"ФГКУ УВО МВД по Удмуртской Республике","NameBash":"Регионсбыт 40","NameLuk":"Регионсбыт ВО"},{"Name":"ВЭЛКОМ ГРУПП","FullName":"ООО Управляющая компания \"ВЭЛКОМ ГРУПП\"","NameBash":"Регионсбыт 23","NameLuk":""},{"Name":"ГБ №3 ","FullName":"БУЗ УР \"ГБ № 3 МЗ УР\"","NameBash":"Регионсбыт 123","NameLuk":""},{"Name":"ГКБ № 2 ","FullName":"БУЗ УР \"ГКБ № 2 МЗ УР\"","NameBash":"Регионсбыт 208","NameLuk":""},{"Name":"ГКБ №1","FullName":"БУЗ УР \"ГКБ №1 МЗ УР\"","NameBash":"Регионсбыт 181","NameLuk":""},{"Name":"ГКБ №7 ","FullName":"БУЗ УР \"ГКБ № 7 МЗ УР\"","NameBash":"Регионсбыт 117","NameLuk":""},{"Name":"ГКБ №7 Детская","FullName":"БУЗ УР \"Детская городская клиническая больница №7 Министерства здравоохранения Удмуртской Республики\"","NameBash":"Регионсбыт 191","NameLuk":""},{"Name":"Глазовская гимназия №6","FullName":"МБОУ \"ГИМНАЗИЯ № 6\"","NameBash":"Регионсбыт 220","NameLuk":""},{"Name":"Глазовская ДЮСШ №1","FullName":"Муниципальное бюджетное образовательное учреждение дополнительного образования детей \"Детско-юношеская спортивная школа №1\" МО \"Город Глазов\"","NameBash":"Регионсбыт 94","NameLuk":""},{"Name":"Глазовский детский дом-интернат для уо детей","FullName":"Глазовский детский дом-интернат для умственно отсталых детей","NameBash":"Регионсбыт 64","NameLuk":""},{"Name":"Галзовский реаб центр РЦДП с огр возможностями","FullName":"Глазовский реабилитационный центр для детей и подростков с ограниченными возможностями","NameBash":"Регионсбыт 206","NameLuk":""},{"Name":"ГЛАЗОВСКИЙ ПСИХОНЕВРОЛОГИЧЕСКИЙ ИНТЕРНАТ","FullName":"ГЛАЗОВСКИЙ ПСИХОНЕВРОЛОГИЧЕСКИЙ ИНТЕРНАТ","NameBash":"Регионсбыт 215","NameLuk":""},{"Name":"Глазовский СРЦДН г.Глазов «СЕМЬЯ»","FullName":"СРЦДН Г ГЛАЗОВА «СЕМЬЯ»","NameBash":"Регионсбыт 77","NameLuk":""},{"Name":"Глазовское лесничество","FullName":"ГКУ УР \"ГЛАЗОВСКОЕ ЛЕСНИЧЕСТВО\"","NameBash":"Регионсбыт 125","NameLuk":""},{"Name":"Горизонт комбинат ФГКУ","FullName":"ФГКУ комбинат \"Горизонт\" Росрезерва","NameBash":"Регионсбыт 110","NameLuk":""},{"Name":"Горнякская школа МБОУ","FullName":"МБОУ \"Горнякская средняя общеобразовательная школа\"","NameBash":"Регионсбыт 174","NameLuk":""},{"Name":"Госинспекция труда","FullName":"Государственная инспекция труда в Удмуртской Республике","NameBash":"Регионсбыт 195","NameLuk":""},{"Name":"Госпиталь ветеранов респ РГВВ ","FullName":"БУЗ УР \"РГВВ МЗ УР\"","NameBash":"Регионсбыт 56","NameLuk":""},{"Name":"ГП №9 Детская","FullName":"БУЗ УР \"ДГП №9 МЗ УР\"","NameBash":"Регионсбыт 188","NameLuk":""},{"Name":"ГПС ГУ","FullName":"Государственное учреждение Удмуртской Республики \"Государственная противопожарная служба Удмуртской Республики\"","NameBash":"Регионсбыт 1","NameLuk":"Регионсбыт ГПС"},{"Name":"ГПС ГУ","FullName":"Государственное учреждение Удмуртской Республики \"Государственная противопожарная служба Удмуртской Республики\"","NameBash":"Регионсбыт 13","NameLuk":"Регионсбыт ГПС Сити"},{"Name":"ГПС ГУ","FullName":"Государственное учреждение Удмуртской Республики \"Государственная противопожарная служба Удмуртской Республики\"","NameBash":"Регионсбыт 47","NameLuk":"Регионсбыт ГПС Бюджет"},{"Name":"Граховская Администрация","FullName":"АДМИНИСТРАЦИЯ ГРАХОВСКОГО РАЙОНА","NameBash":"","NameLuk":"Регионсбыт ГрМО"},{"Name":"Дебесская ЦРБ ","FullName":"БУЗ УР \"ДЕБЁССКАЯ РБ МЗ УР\"","NameBash":"","NameLuk":"Регионсбыт ДЕБРБ"},{"Name":"ДЕБЕССКИЙ ПОЛИТЕХНИКУМ БПОУ УР","FullName":"БПОУ УР \"ДЕБЁССКИЙ ПОЛИТЕХНИКУМ\"","NameBash":"","NameLuk":"Регионсбыт ДебПолТех"},{"Name":"ДЕБЕССКИЙ ПОЛИТЕХНИКУМ БПОУ УР","FullName":"БПОУ УР \"ДЕБЁССКИЙ ПОЛИТЕХНИКУМ\"","NameBash":"","NameLuk":"Регионсбыт Б ДебПолТех"},{"Name":"Детсад №3 УЛЫБКА Кез","FullName":"МБДОУ \"ЦРР-Д/С №3 \"УЛЫБКА\"","NameBash":"","NameLuk":"ЦРР №3 Улыбка"},{"Name":"Диагностический центр РКДЦ ","FullName":"БУЗ УР \"РКДЦ МЗ УР\"","NameBash":"Регионсбыт 102","NameLuk":""},{"Name":"Диагностический центр РКДЦ ","FullName":"БУЗ УР \"РКДЦ МЗ УР\"","NameBash":"Регионсбыт 129","NameLuk":""},{"Name":"Железнодорожный техникум","FullName":"ИТЖТ- филиал СамГУПС","NameBash":"Регионсбыт 3","NameLuk":""},{"Name":"Завьяловская библиотека","FullName":"МБУК \"МЦБС Завьяловского района\"","NameBash":"Регионсбыт 228","NameLuk":""},{"Name":"Завьяловская школа с углубл","FullName":"МБОУ \"ЗАВЬЯЛОВСКАЯ СОШ С УГЛУБЛЕННЫМ ИЗУЧЕНИЕМ ОТДЕЛЬНЫХ ПРЕДМЕТОВ\"","NameBash":"Регионсбыт 88","NameLuk":""},{"Name":"Завьяловский Культурный комплекс \"Центральный\"","FullName":"МБУ \"ККЦ\"","NameBash":"Регионсбыт 219","NameLuk":""},{"Name":"Завьяловский центр безопасност ","FullName":"МБУ \"ЗАВЬЯЛОВСКИЙ ЦЕНТР ОБЕСПЕЧЕНИЯ БЕЗОПАСНОСТИ\"","NameBash":"Регионсбыт 49","NameLuk":""},{"Name":"Зуринская школа Игра ","FullName":"МБОУ ЗУРИНСКАЯ СОШ","NameBash":"Регионсбыт 87","NameLuk":""},{"Name":"Зюзинская школа Шаркан","FullName":"МБОУ \"ЗЮЗИНСКАЯ СОШ\"","NameBash":"","NameLuk":"МБОУ Зюзинская СОШ"},{"Name":"Игринская школа №1","FullName":"МБОУ Игринская СОШ №1","NameBash":"Регионсбыт 176","NameLuk":""},{"Name":"Игринская школа №2","FullName":"МБОУ Игринская СОШ № 2","NameBash":"Регионсбыт 148","NameLuk":""},{"Name":"Игринский ДДТ","FullName":"МБУДО ИГРИНСКИЙ РАЙОННЫЙ ДДТ","NameBash":"Регионсбыт 92","NameLuk":""},{"Name":"Игринский РЦД(Ю)ТТ","FullName":"МБОУ ДОД \"Игринский районный ЦД(Ю)ТТ\"","NameBash":"Регионсбыт 190","NameLuk":""},{"Name":"Игринское МО совет депутатов","FullName":"Совет депутатов муниципального образования \"Игринский район\"","NameBash":"Регионсбыт 21","NameLuk":""},{"Name":"ИЖГЭТ Г.ИЖЕВСКА МУП","FullName":"МУП \"ИЖГЭТ\" Г.ИЖЕВСКА","NameBash":"Регионсбыт 18","NameLuk":""},{"Name":"Ижевский ЛО МВД России на транпорте","FullName":"Ижевский ЛО МВД России на транспорте","NameBash":"Регионсбыт 10","NameLuk":"Регионсбыт ЛО"},{"Name":"ИЖСТРОЙПРОМ ООО","FullName":"ООО \"ИЖСТРОЙПРОМ\"","NameBash":"Регионсбыт 38","NameLuk":""},{"Name":"ИЖТЭП ЗАО","FullName":"ЗАО \"ИЖТЭП\"","NameBash":"Регионсбыт 196","NameLuk":""},{"Name":"ИжЮИ (ф) РПА Минюста Россиии","FullName":"Федеральное государственное бюджетное образовательное учреждение высшего профессионального образования \"Всероссийский государственный университет юстиции (РПА Минюста России)\" Ижевский институт (филиал)","NameBash":"Регионсбыт 22","NameLuk":""},{"Name":"Имекс","FullName":"ЗАО \"НПО \"ИМЕКС\"","NameBash":"Регионсбыт 172","NameLuk":""},{"Name":"Институт механики ","FullName":"ИМ УРО РАН","NameBash":"Регионсбыт 194","NameLuk":""},{"Name":"Инфекционка РКИБ","FullName":"БУЗ УР \"РКИБ МЗ УР\"","NameBash":"Регионсбыт 127","NameLuk":""},{"Name":"ИПОПАТ","FullName":"ОАО \"Ижевское производственное объединение пассажирского автотранспорта\"","NameBash":"Регионсбыт 28","NameLuk":""},{"Name":"КАМА ООО СК","FullName":"ООО СК \"КАМА\"","NameBash":"Регионсбыт 83","NameLuk":""},{"Name":"Кама-Строй ООО","FullName":"ООО \"Кама-Строй\"","NameBash":"Регионсбыт 26","NameLuk":""},{"Name":"Камбарская Администрация","FullName":"АДМИНИСТРАЦИЯ КАМБАРСКОГО РАЙОНА","NameBash":"Регионсбыт 126","NameLuk":""},{"Name":"Камбарская ЦРБ","FullName":"БУЗ УР \"КАМБАРСКАЯ РБ МЗ УР\"","NameBash":"Регионсбыт 39","NameLuk":""},{"Name":"Камбарское МО Администрация","FullName":"АДМИНИСТРАЦИЯ МО \"КАМБАРСКОЕ\" ","NameBash":"Регионсбыт 150","NameLuk":""},{"Name":"Камское судоходство Сарапул филиал","FullName":"Нижне-Камский район водных путей и судоходства - филиал ФБУ \"Администрация Камского бассейна внутренних водных путей\"","NameBash":"Регионсбыт 147","NameLuk":""},{"Name":"Камуралрыбвод головное   ","FullName":"ФГБУ \"КАМУРАЛРЫБВОД\"","NameBash":"Регионсбыт 124","NameLuk":""},{"Name":"Канифольный детский дом-интернат","FullName":"Канифольный детский дом-интернат","NameBash":"Регионсбыт 211","NameLuk":""},{"Name":"Каракулинская ЦРБ ","FullName":"БУЗ УР \"КАРАКУЛИНСКАЯ РБ МЗ УР\"","NameBash":"Регионсбыт 74","NameLuk":""},{"Name":"Каракулинская школа-интернат","FullName":"МКОУДДСИДОБПР \"КАРАКУЛИНСКАЯ СПЕЦИАЛЬНАЯ (КОРРЕКЦИОННАЯ) ШКОЛА-ИНТЕРНАТ\"","NameBash":"Регионсбыт 221","NameLuk":""},{"Name":"Кватчинская школа Можга","FullName":"МБОУ \"Кватчинская СОШ\"","NameBash":"Регионсбыт 154","NameLuk":""},{"Name":"Кезская ДЮСШ","FullName":"МБУДО \"КЕЗСКАЯ РАЙОННАЯ ДЮСШ\"","NameBash":"","NameLuk":"Регионсбыт КезДЮСШ"},{"Name":"Кезская ЦРБ","FullName":"БУЗ УР \"Кезская РБ МЗ УР\"","NameBash":"","NameLuk":"Регионсбыт КЕЗРБ"},{"Name":"Кезская школа №2","FullName":"МБОУ \"КЕЗСКАЯ СОШ №2\"","NameBash":"","NameLuk":"Кезская СОШ №2"},{"Name":"КЕЗСКИЙ РАЙОННЫЙ СОВЕТ ДЕПУТАТОВ","FullName":"КЕЗСКИЙ РАЙОННЫЙ СОВЕТ ДЕПУТАТОВ","NameBash":"","NameLuk":"Регионсбыт СДКез"},{"Name":"Кекоранская школа Якшур-Бодья","FullName":"МОУ \"КЕКОРАНСКАЯ СОШ\"","NameBash":"Регионсбыт 75","NameLuk":"Регионсбыт КекСОШ"},{"Name":"Кильмезская школа Сюмси","FullName":"МБОУ \"Кильмезская СОШ\"","NameBash":"","NameLuk":"Регионсбыт КСОШ"},{"Name":"Кож. вен РКВД ","FullName":"БУЗ УР \"РКВД МЗ УР\"","NameBash":"Регионсбыт 166","NameLuk":""},{"Name":"Кож. вен РКВД ","FullName":"БУЗ УР \"РКВД МЗ УР\"","NameBash":"Регионсбыт 182","NameLuk":""},{"Name":"Компания Сити","FullName":"Емелин","NameBash":"Регионсбыт","NameLuk":""},{"Name":"Красногорская детская школа искусств","FullName":"МБУ ДО \"КРАСНОГОРСКАЯ ДШИ\"","NameBash":"Регионсбыт 169","NameLuk":""},{"Name":"Красногорская ЦРБ","FullName":"БУЗ  УР \"Красногорская районная больница Министерства здравоохранения Удмуртской республики\"","NameBash":"Регионсбыт 193","NameLuk":""},{"Name":"Красногорская школа","FullName":"Красногорская школа","NameBash":"Регионсбыт 76","NameLuk":""},{"Name":"Красногорский дом ремесел","FullName":"МБУК \"КРАСНОГОРСКИЙ ДР\"","NameBash":"Регионсбыт 168","NameLuk":""},{"Name":"Красногорский культурно-спортивный комплекс межпос","FullName":"МБУ МКСК \"КРАСНОГОРСКИЙ\"","NameBash":"Регионсбыт 192","NameLuk":""},{"Name":"Красногорский отдел культуры,спорта и МП","FullName":"ОКСИМП АДМИНИСТРАЦИИ МО \"КРАСНОГОРСКИЙ РАЙОН\"","NameBash":"Регионсбыт 145","NameLuk":""},{"Name":"Кузьминская школа Кез","FullName":"МБОУ \"КУЗЬМИНСКАЯ СОШ\"","NameBash":"","NameLuk":"Кузьминская СОШ"},{"Name":"Кулигинская школа Кез","FullName":"МБОУ \"КУЛИГИНСКАЯ СОШ\"","NameBash":"","NameLuk":"Кулигинская СОШ"},{"Name":"Курсы Гражд Обороны Ижевска","FullName":"МБУ ДПО \"Курсы ГО города Ижевска\"","NameBash":"Регионсбыт 136","NameLuk":""},{"Name":"Курьинская школа Красногор","FullName":"МБОУ КУРЬИНСКАЯ СОШ","NameBash":"Регионсбыт 160","NameLuk":""},{"Name":"Кушьинская школа Игра","FullName":"МБОУ Кушьинская СОШ","NameBash":"Регионсбыт 161","NameLuk":""},{"Name":"КЦСОН Глазов город","FullName":"КЦСОН Г.ГЛАЗОВА","NameBash":"Регионсбыт 186","NameLuk":""},{"Name":"КЦСОН Глазовского района","FullName":"КЦСОН Глазовского района","NameBash":"Регионсбыт 104","NameLuk":""},{"Name":"КЦСОН Завьяловского района","FullName":"КЦСОН ЗАВЬЯЛОВСКОГО РАЙОНА","NameBash":"Регионсбыт 103","NameLuk":""},{"Name":"Администрация Камбарского района (целевые)","FullName":"АДМИНИСТРАЦИЯ КАМБАРСКОГО РАЙОНА","NameBash":"Регионсбыт 205","NameLuk":""},{"Name":"ЛАЗТЕХ ","FullName":"ООО \"ЛАЗТЕХ\"","NameBash":"Регионсбыт 51","NameLuk":""},{"Name":"ЛЕСНИЧЕСТВО ИМ. Б.К.ФИЛИМОНОВА ГКУ УР","FullName":"ГКУ УР \"ЛЕСНИЧЕСТВО ИМ. Б.К.ФИЛИМОНОВА\"","NameBash":"Регионсбыт 167","NameLuk":""},{"Name":"Лозинская школа Игра","FullName":"МБОУ \"Лозинская ООШ\"","NameBash":"Регионсбыт 162","NameLuk":""},{"Name":"Лолошур-Возжинская школа Грахово","FullName":"МБОУ \"ЛОЛОШУР-ВОЗЖИНСКАЯ СРЕДНЯЯ ОБЩЕОБРАЗОВАТЕЛЬНАЯ ШКОЛА\"","NameBash":"","NameLuk":"Регионсбыт Л-возж СОШ"},{"Name":"Лынгинская школа Якшур-Бод ","FullName":"МБОУ ЛЫНГИНСКАЯ СОШ","NameBash":"Регионсбыт 226","NameLuk":"Регионсбыт ЛынСОШ"},{"Name":"Люкская школа Завьялово","FullName":"МБОУ \"ЛЮКСКАЯ СОШ\"","NameBash":"Регионсбыт 114","NameLuk":""},{"Name":"Малопургинская гимназия","FullName":"МОУ ГИМНАЗИЯ С. МАЛАЯ ПУРГА","NameBash":"Регионсбыт 68","NameLuk":""},{"Name":"Малопургинская Межпосел ЦБС ","FullName":"МУК \"МАЛОПУРГИНСКАЯ МЕЖПОСЕЛЕНЧЕСКАЯ ЦБС\"","NameBash":"Регионсбыт 155","NameLuk":""},{"Name":"Малопургинская школа № 1","FullName":"МОУ СОШ №1 С.МАЛАЯ ПУРГА","NameBash":"Регионсбыт 86","NameLuk":""},{"Name":"Малопургинская школа Баграш-Бигра ","FullName":"МОУ СОШ Д.БАГРАШ-БИГРА","NameBash":"Регионсбыт 222","NameLuk":""},{"Name":"Малопургинская школа Гожня","FullName":"МОУ СОШ Д. ГОЖНЯ","NameBash":"Регионсбыт 204","NameLuk":""},{"Name":"Малопургинский краеведческий музей","FullName":"МБУК \"МРКМ\"","NameBash":"Регионсбыт 202","NameLuk":""},{"Name":"Малопургинский центр образован","FullName":"МВОУ \"Малопургинский Центр образования\"","NameBash":"Регионсбыт 183","NameLuk":""},{"Name":"МЕГАЛЮКС ООО","FullName":"ООО \"МЕГАЛЮКС\"","NameBash":"Регионсбыт 91","NameLuk":""},{"Name":"МЕДВЕДЬ ООО","FullName":"ООО \"МЕДВЕДЬ\"","NameBash":"Регионсбыт 115","NameLuk":""},{"Name":"МЕЖРАЙОННАЯ ИМНС РОССИИ №6 ПО УДМУРТСКОЙ РЕСПУБЛИКЕ","FullName":"МЕЖРАЙОННАЯ ИМНС РОССИИ №6 ПО УДМУРТСКОЙ РЕСПУБЛИКЕ","NameBash":"Регионсбыт 151","NameLuk":""},{"Name":"МЕЖРАЙОННАЯ ИФНС РОССИИ № 7 ПО УДМУРТСКОЙ РЕСПУБЛИКЕ","FullName":"МЕЖРАЙОННАЯ ИФНС РОССИИ № 7 ПО УДМУРТСКОЙ РЕСПУБЛИКЕ","NameBash":"Регионсбыт 227","NameLuk":""},{"Name":"Мин. сельского хозяйства","FullName":" МИНИСТЕРСТВО СЕЛЬСКОГО ХОЗЯЙСТВА И ПРОДОВОЛЬСТВИЯ УДМУРТСКОЙ РЕСПУБЛИКИ","NameBash":"Регионсбыт 15","NameLuk":""},{"Name":"Министерство лесного хозяйства","FullName":"Министерство лесного хозяйства Удмуртской Республики","NameBash":"Регионсбыт 140","NameLuk":""},{"Name":"МИНПРИРОДЫ УР","FullName":"МИНПРИРОДЫ УР","NameBash":"Регионсбыт 4","NameLuk":"Регионсбыт ФФ"},{"Name":"Мировые судьи УправлОДМС","FullName":"Управление по обеспечению деятельности мировых судей УР при Правительстве УР  ","NameBash":"Регионсбыт 84","NameLuk":""},{"Name":"Мировые судьи УправлОДМС","FullName":"Управление по обеспечению деятельности мировых судей УР при Правительстве УР  ","NameBash":"Регионсбыт 199","NameLuk":""},{"Name":"Можгинская Администрация  ","FullName":" АДМИНИСТРАЦИЯ МОЖГИНСКОГО РАЙОНА","NameBash":"Регионсбыт 152","NameLuk":""},{"Name":"Можгинская ДЮСШ","FullName":"МКОУ ДО \"ДЮСШ МОЖГИНСКОГО РАЙОНА\"","NameBash":"Регионсбыт 187","NameLuk":""},{"Name":"Можгинский ДДТ","FullName":"МКОУ ДО \"ДДТ МОЖГИНСКОГО РАЙОНА\"","NameBash":"Регионсбыт 149","NameLuk":""},{"Name":"Можгинский ИМЦ","FullName":"МБУ Можгинского района \"Информационно Методический Центр\"","NameBash":"Регионсбыт 14","NameLuk":""},{"Name":"Можгинский отдел культуры","FullName":"МКУ \"ОТДЕЛ КУЛЬТУРЫ МОЖГИНСКОГО РАЙОНА\"","NameBash":"Регионсбыт 32","NameLuk":""},{"Name":"Можгинский район МО Сов депут","FullName":"Совет депутатов муниципального образования \"Можгинский район\"","NameBash":"Регионсбыт 73","NameLuk":""},{"Name":"МОЛСБЫТ ООО","FullName":"ООО \"МОЛСБЫТ\"","NameBash":"Регионсбыт 12","NameLuk":""},{"Name":"МСЧ МВД России ФКУЗ по УР","FullName":"ФКУЗ \"МСЧ МВД России по Удмуртской республике\"","NameBash":"Регионсбыт 165","NameLuk":""},{"Name":"Мукшинская СОШ Якшур-Бодьин","FullName":"МБОУ \"Мукшинская средняя общеобразовательная школа\"","NameBash":"Регионсбыт 70","NameLuk":""},{"Name":"Нагорный психоневрологический ","FullName":"НАГОРНЫЙ ПСИХОНЕВРОЛОГИЧЕСКИЙ ИНТЕРНАТ","NameBash":"Регионсбыт 5","NameLuk":""},{"Name":"НИТИ ПРОГРЕСС ОАО","FullName":"ОАО \"НИТИ \"ПРОГРЕСС\"","NameBash":"Регионсбыт 224","NameLuk":""},{"Name":"Новоунтемская школа Кез","FullName":"МКОУ \"НОВОУНТЕМСКАЯ СОШ\"","NameBash":"","NameLuk":"Новоутемская СОШ"},{"Name":"Нышинский детский сад Можга","FullName":"МБДОУ \"Нышинский детский сад\"","NameBash":"Регионсбыт 106","NameLuk":""},{"Name":"Озоно-Чепецкая школа-интернат Кез","FullName":"МСОУ \"ОЗОНО-ЧЕПЕЦКАЯ ШКОЛА-ИНТЕРНАТ\"","NameBash":"","NameLuk":"Озоно-Чепецкая КШИ"},{"Name":"Онкодиспансер РКОД","FullName":"БУЗ УР \"РКОД ИМ. С.Г.  ПРИМУШКО МЗ УР\"","NameBash":"Регионсбыт 30","NameLuk":""},{"Name":"Пажманская школа Кез","FullName":"МКОУ \"ПАЖМАНСКАЯ ООШ\"","NameBash":"","NameLuk":"Пажманская СОШ"},{"Name":"Папирус","FullName":"ООО НПП \"Папирус\"","NameBash":"Регионсбыт 178","NameLuk":""},{"Name":"Параллель ООО","FullName":"ООО \"Параллель\"","NameBash":"Регионсбыт 120","NameLuk":""},{"Name":"Первая респ псих больница Сардан","FullName":"ГКУЗ \"1-АЯ РПБ МЗ УР\"","NameBash":"Регионсбыт 210","NameLuk":""},{"Name":"Первая республиканская больница","FullName":"БУЗ УР \"ПЕРВАЯ РЕСПУБЛИКАНСКАЯ КЛИНИЧЕСКАЯ БОЛЬНИЦА МЗ УР\"","NameBash":"Регионсбыт 35","NameLuk":""},{"Name":"Первая республиканская больница","FullName":"БУЗ УР \"ПЕРВАЯ РЕСПУБЛИКАНСКАЯ КЛИНИЧЕСКАЯ БОЛЬНИЦА МЗ УР\"","NameBash":"Регионсбыт 72","NameLuk":""},{"Name":"Первая республиканская больница","FullName":"БУЗ УР \"ПЕРВАЯ РЕСПУБЛИКАНСКАЯ КЛИНИЧЕСКАЯ БОЛЬНИЦА МЗ УР\"","NameBash":"Регионсбыт 78","NameLuk":""},{"Name":"Пермская Таможня","FullName":"Пермская Таможня","NameBash":"Регионсбыт 93","NameLuk":""},{"Name":"Пожарная часть 8","FullName":"ФКУ \"8 ПЧ ФПС ГПС по Удмуртской Республике (договорная)\"","NameBash":"Регионсбыт 101","NameLuk":""},{"Name":"Поломская школа №2 Кез","FullName":"МБОУ \"ПОЛОМСКАЯ СОШ № 2\"","NameBash":"","NameLuk":"Поломская СОШ №2"},{"Name":"ПРЕСТИЖ ООО","FullName":"ООО \"ПРЕСТИЖ\"","NameBash":"Регионсбыт 213","NameLuk":""},{"Name":"Психиатрич респ № 3","FullName":"ГКУЗ \"3 РПБ МЗ УР\"","NameBash":"Регионсбыт 207","NameLuk":""},{"Name":"Психиатрическая","FullName":"БУЗ и СПЭ УР \"РКПБ МЗ УР\"","NameBash":"Регионсбыт 137","NameLuk":""},{"Name":"ПСС Ижевск","FullName":"Муниципальное бюджетное учреждение \"Поисково-спасательная служба города Ижевска\"","NameBash":"Регионсбыт 29","NameLuk":""},{"Name":"ПСС УР ","FullName":"ГУ УР \"ПСС УР\"","NameBash":"Регионсбыт 141","NameLuk":""},{"Name":"Пудемская школа Яр","FullName":"МКОУ \"Пудемская средняя общеобразовательная школа\"","NameBash":"","NameLuk":"Регионсбыт ПУДСОЖ"},{"Name":"Пужмезьская школа Кез","FullName":"МБОУ \"ПУЖМЕЗЬСКАЯ ООШ\" КЕЗСКОГО РАЙОНА УР","NameBash":"","NameLuk":"Пужмезьская ООШ"},{"Name":"ПФР управление Воткинск ","FullName":"УПФР ПО Г.ВОТКИНСКУ, ВОТКИНСКОМУ И ШАРКАНСКОМУ РАЙОНАМ УДМУРТСКОЙ РЕСПУБЛИКИ (МЕЖРАЙОННОЕ)","NameBash":"Регионсбыт 118","NameLuk":""},{"Name":"ПФР управление Грахов р-н","FullName":"Управление Пенсионного фонда РФ (государственное учреждение) в Граховском районе Удмуртской Республики","NameBash":"","NameLuk":"Регионсбыт ГрПФР"},{"Name":"ПФР управление Кезский р-н","FullName":"УПФР В КЕЗСКОМ РАЙОНЕ УДМУРТСКОЙ РЕСПУБЛИКИ","NameBash":"","NameLuk":"Регионсбыт ПФР Кез"},{"Name":"ПФР управление Киясовский р-н","FullName":"УПФР В КИЯСОВСКОМ РАЙОНЕ УДМУРТСКОЙ РЕСПУБЛИКИ","NameBash":"Регионсбыт 184","NameLuk":""},{"Name":"ПФР управление Можгинский р-н","FullName":"УПФР В ГОРОДЕ МОЖГЕ И МОЖГИНСКОМ РАЙОНЕ УДМУРТСКОЙ РЕСПУБЛИКИ","NameBash":"Регионсбыт 34","NameLuk":""},{"Name":"ПФР управление Сарапул","FullName":"УПФР В Г. САРАПУЛЕ УДМУРТСКОЙ РЕСПУБЛИКИ (МЕЖРАЙОННОЕ)","NameBash":"Регионсбыт 158","NameLuk":""},{"Name":"Пычасская школа Можга","FullName":"МБОУ \"Пычасская СОШ\"","NameBash":"Регионсбыт 157","NameLuk":""},{"Name":"Реабил центр Воткинск СРЦДН Г. ВОТКИНСКА","FullName":"СРЦДН Г. ВОТКИНСКА","NameBash":"Регионсбыт 216","NameLuk":""},{"Name":"Реабил центр республ","FullName":"ГКУ СО УР \"Республиканский социально-реабилитационный центр для несовершеннолетних\"","NameBash":"Регионсбыт 31","NameLuk":""},{"Name":"Респуб больница мед реабил РБМР Кизнер","FullName":"БУЗ УР \"РБМР МЗ УР\"","NameBash":"Регионсбыт 113","NameLuk":""},{"Name":"Республиканская детская клинич больница","FullName":"БУЗ  УР \"РДКБ МЗ УР\"","NameBash":"Регионсбыт 48","NameLuk":""},{"Name":"Ресторанная коллекция","FullName":"ООО \"РЕСТОРАННАЯ КОЛЛЕКЦИЯ\"","NameBash":"Регионсбыт 20","NameLuk":""},{"Name":"Росреестр филиал УР","FullName":"ФГБУ \"ФКП Росреестра\" филиал ФГБУ \"ФКП Росреестра\" по Удмуртской Республике","NameBash":"Регионсбыт 198","NameLuk":""},{"Name":"РОССЕЛЬХОЗБАНК АО","FullName":"АО \"РОССЕЛЬХОЗБАНК\"","NameBash":"Регионсбыт 16","NameLuk":"Регионсбыт РСБ"},{"Name":"Россельхозцентр по УР","FullName":"Филиал ФГБУ \"Россельхозцентр\" по Удмуртской Республике","NameBash":"Регионсбыт 112","NameLuk":""},{"Name":"Рыболовство Самара","FullName":"СРЕДНЕВОЛЖСКОЕ ТУ РОСРЫБОЛОВСТВА","NameBash":"Регионсбыт 179","NameLuk":""},{"Name":"Сарапул.политех","FullName":"БПОУ УР \"Сарапульский политехнологический техникум\"","NameBash":"Регионсбыт 164","NameLuk":""},{"Name":"Сарапульская Адм город","FullName":"АДМИНИСТРАЦИЯ ГОРОДА САРАПУЛА","NameBash":"Регионсбыт 197","NameLuk":""},{"Name":"Сарапульская Администрация район","FullName":"АДМИНИСТРАЦИЯ МУНИЦИПАЛЬНОГО ОБРАЗОВАНИЯ \"САРАПУЛЬСКИЙ РАЙОН\"","NameBash":"Регионсбыт 209","NameLuk":""},{"Name":"Сарапульская городская больница №1 ","FullName":"БУЗ УР \"САРАПУЛЬСКАЯ ГБ № 1 МЗ УР\"","NameBash":"Регионсбыт 79","NameLuk":""},{"Name":"Сарапульская детская городская больница","FullName":"БУЗ УР \"САРАПУЛЬСКАЯ ГДБ МЗ УР\"","NameBash":"Регионсбыт 135","NameLuk":""},{"Name":"Сарапульский роддом","FullName":"БУЗ УР \"САРАПУЛЬСКИЙ МРД МЗ УР\"","NameBash":"Регионсбыт 203","NameLuk":""},{"Name":"Селтинская ЦРБ","FullName":"БУЗ УР \"СЕЛТИНСКАЯ РБ МЗ УР\"","NameBash":"Регионсбыт 119","NameLuk":""},{"Name":"Сельхозакадемия ","FullName":"ФГБОУ ВО ИЖЕВСКАЯ ГСХА","NameBash":"Регионсбыт 217","NameLuk":""},{"Name":"Сергинская школа Балезин","FullName":"МБОУ \"СЕРГИНСКАЯ СРЕДНЯЯ ШКОЛА\"","NameBash":"Регионсбыт 159","NameLuk":""},{"Name":"Сигаевская школа","FullName":"МБОУ Сигаевская СОШ","NameBash":"Регионсбыт 80","NameLuk":""},{"Name":"Следственный комитет","FullName":"Следственное управление Следственного комитета РФ по УР","NameBash":"Регионсбыт 62","NameLuk":""},{"Name":"Служба благоустройства Ижевск СБИДХ","FullName":"МКУ Г.ИЖЕВСКА \"СБИДХ\"","NameBash":"Регионсбыт 61","NameLuk":""},{"Name":"Служба заказчика по СР и КР Сарапул","FullName":"МУ г.Сарапула \"Служба заказчика по СР и КР\"","NameBash":"Регионсбыт 90","NameLuk":""},{"Name":"СМНП ЖКХ УР ООО","FullName":"ООО \"СМНП ЖКХ УР\"","NameBash":"Регионсбыт 44","NameLuk":""},{"Name":"Спид","FullName":"БУЗ УР \"УРЦ СПИД И ИЗ\"","NameBash":"Регионсбыт 11","NameLuk":""},{"Name":"Староберезнякская школа Можга","FullName":"МКОУ \"СТАРОБЕРЕЗНЯКСКАЯ СОШ\"","NameBash":"Регионсбыт 201","NameLuk":""},{"Name":"Старокаксинская школа Можга","FullName":"МБОУ \"Старокаксинская СОШ\"","NameBash":"Регионсбыт 43","NameLuk":""},{"Name":"Старомоньинский дом ремесел Малая Пурга","FullName":"МБУК \"СТАРОМОНЬИНСКИЙ ДОМ РЕМЁСЕЛ\"","NameBash":"Регионсбыт 223","NameLuk":""},{"Name":"Статистика ТоФсгс","FullName":"УДМУРТСТАТ","NameBash":"Регионсбыт 36 ","NameLuk":""},{"Name":"Степаненская школа Кез","FullName":"МБОУ \"СТЕПАНЕНСКАЯ СОШ\"","NameBash":"","NameLuk":"Степаненская СОШ"},{"Name":"СТЕХ ","FullName":"ООО \"СОВРЕМЕННЫЕ СТРОИТЕЛЬНЫЕ ТЕХНОЛОГИИ\" (ООО \"СТЕХ\")","NameBash":"Регионсбыт 97","NameLuk":""},{"Name":"СТО ЖКХ МКУ города Ижевска","FullName":"МКУ ГОРОДА ИЖЕВСКА \"СТО ЖКХ\"","NameBash":"Регионсбыт 225","NameLuk":""},{"Name":"Судебные приставы УФССП","FullName":"УФССП РОССИИ ПО УДМУРТСКОЙ РЕСПУБЛИКЕ","NameBash":"Регионсбыт 55","NameLuk":"Регионсбыт СП"},{"Name":"Судебный департамент  ","FullName":"УПРАВЛЕНИЕ СУДЕБНОГО ДЕПАРТАМЕНТА В УДМУРТСКОЙ РЕСПУБЛИКЕ","NameBash":"Регионсбыт 53","NameLuk":"Регионсбыт СД"},{"Name":"Сюмсинская Администрация","FullName":"АДМИНИСТРАЦИЯ СЮМСИНСКОГО РАЙОНА","NameBash":"","NameLuk":"Регионсбыт СюмАдм"},{"Name":"СЮМСИНСКАЯ ЦРБ","FullName":"БУЗ УР \"СЮМСИНСКАЯ РБ МЗ УР\"","NameBash":"","NameLuk":"Регионсбыт СюмРБ"},{"Name":"Сюмсинское ЖКХ","FullName":"МУП \"ЖКХ \"СЮМСИНСКОЕ\"","NameBash":"Регионсбыт 146","NameLuk":"Регионсбыт СЖКХ"},{"Name":"Тер фонд ОМС","FullName":"ТФОМС УР ","NameBash":"Регионсбыт 133","NameLuk":""},{"Name":"Территориальное ЖКХ","FullName":"ГУП \"Территориальное производственное объеденение жилищно-коммунального хозяйства УР\"","NameBash":"Регионсбыт 24","NameLuk":""},{"Name":"туб РКТБ МЗ УР","FullName":"БУЗ УР \"РКТБ МЗ УР\"","NameBash":"Регионсбыт 8","NameLuk":""},{"Name":"Увинская Администрация","FullName":"Администрация муниципального образования \"Увинский район\"","NameBash":"Регионсбыт 105","NameLuk":""},{"Name":"Увинская ЦРБ","FullName":"БУЗ УР \"Увинская РБ МЗ УР\"","NameBash":"Регионсбыт 98","NameLuk":"Регионсбыт УЦРБ"},{"Name":"Увинская ЦРБ","FullName":"БУЗ УР \"Увинская РБ МЗ УР\"","NameBash":"Регионсбыт 100","NameLuk":""},{"Name":"Угловской респ туб санаторий","FullName":"БУЗ УР \"УРТС МЗ УР\"","NameBash":"Регионсбыт 214","NameLuk":""},{"Name":"Уканская школа Ярский р-н","FullName":"Муниципальное казенное общеобразовательное учреждение \"Уканская средняя общеобразовательная школа\"","NameBash":"","NameLuk":"Регионсбыт УКАНСОШ"},{"Name":"УКС Правительства УР","FullName":"КУ УР \"УКС ПРАВИТЕЛЬСТВА УР\"","NameBash":"Регионсбыт 33","NameLuk":""},{"Name":"Управление образ Воткинск","FullName":"Управление образования Администрации города Воткинск","NameBash":"Регионсбыт 96","NameLuk":""},{"Name":"Управление образ Кез","FullName":"УПРАВЛЕНИЕ ОБРАЗОВАНИЕМ АДМИНИСТРАЦИИ МО \"КЕЗСКИЙ РАЙОН\"","NameBash":"","NameLuk":"УО Кезский район"},{"Name":"Управление образ МалоПург","FullName":"Управление народного образования Администрации муниципального образования \"Малопургинский район\"","NameBash":"Регионсбыт 17","NameLuk":""},{"Name":"Управление образ Увинского района","FullName":"УПРАВЛЕНИЕ ОБРАЗОВАНИЯ УВИНСКОГО РАЙОНА (УВИНСКОЕ УО)","NameBash":"Регионсбыт 50","NameLuk":""},{"Name":"Управление образ Шаркан р-на","FullName":"УПРАВЛЕНИЕ ОБРАЗОВАНИЯ ШАРКАНСКОГО РАЙОНА","NameBash":"","NameLuk":"Регионсбыт УОШ"},{"Name":"Управление образ Юкамен р-на","FullName":"Отдел образования Администрации муниципального образования \"Юкаменский район\"","NameBash":"","NameLuk":"Регионсбыт ОО МО Юкам"},{"Name":"Управление образ Якшур-Бодьин","FullName":"Управление народного образования Администрации муниципального образования \"Якшур-Бодьинский район\"","NameBash":"Регионсбыт 130","NameLuk":""},{"Name":"Управление прир ресурс","FullName":"Функциональный орган Администрации города Ижевска-Управление природных ресурсов и охраны окружающей среды Администрации г.Ижевска","NameBash":"Регионсбыт 128","NameLuk":""},{"Name":"УПРАВЛЕНИЕ РОССЕЛЬХОЗНАДЗОРА КИРОВ и УР","FullName":"УПРАВЛЕНИЕ РОССЕЛЬХОЗНАДЗОРА ПО КИРОВСКОЙ ОБЛАСТИ И УДМУРТСКОЙ РЕСПУБЛИКЕ","NameBash":"Регионсбыт 212","NameLuk":"Регионсбыт РСН"},{"Name":"Управление финансов Адм Можг  ","FullName":"УПРАВЛЕНИЕ ФИНАНСОВ МОЖГИНСКОГО РАЙОНА, УФ МОЖГИНСКОГО РАЙОНА","NameBash":"Регионсбыт 59","NameLuk":""},{"Name":"Управление ФС кадастрКартограф УР","FullName":"Управление Федеральной службы государственной регистрации, кадастра и картографии по Удмуртской Республике","NameBash":"Регионсбыт 27","NameLuk":"Регионсбыт КАД"},{"Name":"Управление ФСБ","FullName":"УФСБ РОССИИ ПО УДМУРТСКОЙ РЕСПУБЛИКЕ","NameBash":"Регионсбыт 170","NameLuk":""},{"Name":"Факельская школа Игра","FullName":"МБОУ \"Факельская СОШ\"","NameBash":"Регионсбыт 63","NameLuk":""},{"Name":"ФГБУ ПТЦ","FullName":"ФГБУ \"Производственно-технический центр федеральной противопожарной службы по Удмуртской Республике\"","NameBash":"Регионсбыт 171","NameLuk":""},{"Name":"Физдиспансер РВФД","FullName":"БУЗ УР \"РВФД МЗ УР\"","NameBash":"Регионсбыт 173","NameLuk":""},{"Name":"Физико-технический институт ","FullName":"ФТИ УРО РАН","NameBash":"Регионсбыт 71","NameLuk":""},{"Name":"ФКУ ИК-5 УФСИН России по УР","FullName":"ФКУ ИК-5 УФСИН России по Удмуртской Республике","NameBash":"Регионсбыт 218","NameLuk":""},{"Name":"ФКУ ИК-6 УФСИН по УР","FullName":"ФКУ ИК № 6 УФСИН по УР","NameBash":"Регионсбыт 45","NameLuk":""},{"Name":"ФКУ ИК-7 УФСИН России","FullName":"ФКУ ИК-7 УФСИН России","NameBash":"Регионсбыт 6","NameLuk":""},{"Name":"ФКУ ИК-8 УФСИН","FullName":"ФКУ ИК-8 УФСИН России по Удмуртской Республике","NameBash":"Регионсбыт 95","NameLuk":""},{"Name":"ФКУ Колония поселение № 11","FullName":"Федеральное Казенное учреждение \"Колония-поселение № 11 УФСИН России по УР\"","NameBash":"Регионсбыт 175","NameLuk":""},{"Name":"ФКУ ЛИУ-4 УФСИН ","FullName":"ФКУ ЛИУ-4 УФСИН РОССИИ ПО УДМУРТСКОЙ РЕСПУБЛИКЕ","NameBash":"Регионсбыт 19","NameLuk":""},{"Name":"ФКУ ЛИУ-4 УФСИН ","FullName":"ФКУ ЛИУ-4 УФСИН РОССИИ ПО УДМУРТСКОЙ РЕСПУБЛИКЕ","NameBash":"Регионсбыт 42","NameLuk":""},{"Name":"ФСС","FullName":"Государственное учреждение -региональное отделение Фонда социального страхования РФ по УР","NameBash":"Регионсбыт 58","NameLuk":""},{"Name":"Центр гигиены","FullName":"ФБУЗ \"ЦЕНТР ГИГИЕНЫ И ЭПИДЕМИОЛОГИИ В УДМУРТСКОЙ РЕСПУБЛИКЕ\"","NameBash":"Регионсбыт 109","NameLuk":""},{"Name":"Центр гигиены Воткинск","FullName":"Филиал ФБУЗ \"Центр гигиены и эпидемиологии в Удмуртской Республике\" в городе Воткинске","NameBash":"Регионсбыт 41","NameLuk":""},{"Name":"Центр гигиены Глазов","FullName":"Филиал Федерального бюджетного учреждения здравоохранения \"Центр гигиены и эпидемиологии в Удмуртской Республике\" г. Глазова","NameBash":"Регионсбыт 2","NameLuk":""},{"Name":"Центр гигиены Игра","FullName":"Филиал ФБУЗ \"Центр гигиены и эпидемиологии в Удмуртской Республике\" в поселке Игра","NameBash":"Регионсбыт 153","NameLuk":""},{"Name":"Центр гигиены Можга","FullName":"Филиал ФБУЗ \"Центр гигиены и эпидемиологии в Удмуртской Республике\" в городе Можга","NameBash":"Регионсбыт 81","NameLuk":""},{"Name":"Центр гигиены Сарапул","FullName":"Филиал ФБУЗ \"Центр гигиены и эпидемиологии в Удмуртской Республике\" в городе Сарапуле","NameBash":"Регионсбыт 52","NameLuk":""},{"Name":"Центр гигиены Ува","FullName":"Филиал ФБУЗ \"Центр гигиены и эпидемиологии в Удмуртской Республике\" в поселке Ува","NameBash":"Регионсбыт 142","NameLuk":""},{"Name":"Центр избир ком","FullName":"Центральная избирательная комиссия Удмуртской Республики","NameBash":"Регионсбыт 180","NameLuk":""},{"Name":"ЦЕНТР КОММЕРЧЕСКОГО УПРАВЛЕНИЯ ООО","FullName":"ООО \"ЦЕНТР КОММЕРЧЕСКОГО УПРАВЛЕНИЯ\"","NameBash":"Регионсбыт 85","NameLuk":""},{"Name":"Центр содержания иностранцев","FullName":"ГКУ УР ЦСИГИЛБГ","NameBash":"Регионсбыт 156","NameLuk":""},{"Name":"Центр спецсвязи и инф ФСОхраны  ","FullName":"ЦЕНТР СПЕЦИАЛЬНОЙ СВЯЗИ И ИНФОРМАЦИИ ФЕДЕРАЛЬНОЙ СЛУЖБЫ ОХРАНЫ РОССИЙСКОЙ ФЕДЕРАЦИИ В УДМУРТСКОЙ РЕСПУБЛИКЕ","NameBash":"Регионсбыт 138","NameLuk":""},{"Name":"ЦЛАТИ филиал грузоплучатель","FullName":"Филиал \"ЦЛАТИ по Удмуртской Республике\" ФГБУ \"Центр лабораторного анализа и технических измерений по Приволжскому федеральному округу\"","NameBash":"Регионсбыт 37","NameLuk":""},{"Name":"Чепецкая школа Кез","FullName":"МБОУ \"ЧЕПЕЦКАЯ СОШ\"","NameBash":"","NameLuk":"Чепецкая СОШ"},{"Name":"Чумойская школа Игра","FullName":"МБОУ ЧУМОЙСКАЯ НОШ","NameBash":"Регионсбыт 185","NameLuk":""},{"Name":"Чутырская школа Игра","FullName":"МБОУ \"Чутырская СОШ\"","NameBash":"Регионсбыт 60","NameLuk":""},{"Name":"Шабердинск. муницип. образован","FullName":"Администрация муниципального образования \"Шабердинское\"","NameBash":"Регионсбыт 163","NameLuk":""},{"Name":"Шарканская Администрация ","FullName":"АДМИНИСТРАЦИЯ ШАРКАНСКОГО РАЙОНА","NameBash":"Регионсбыт 122","NameLuk":""},{"Name":"Шарканская школа ","FullName":"МБОУ ШАРКАНСКАЯ СОШ","NameBash":"","NameLuk":"МБО Шарканская СОШ"},{"Name":"Электромонтаж","FullName":"ООО \"Строительно-монтажная фирма \"Электромонтаж\"","NameBash":"Регионсбыт 189","NameLuk":""},{"Name":"Электросила ","FullName":"ООО  \"Электросила\"","NameBash":"Регионсбыт 82","NameLuk":""},{"Name":"Энергия Якшур-Бодья","FullName":"ООО \"ЭНЕРГИЯ\"","NameBash":"Регионсбыт 69","NameLuk":""},{"Name":"Юкаменская Адм","FullName":"Администрация муниципального образования \"Юкаменский район\"","NameBash":"","NameLuk":"Регионсбыт ЮМО"},{"Name":"ЮКАМЕНСКАЯ ЦРБ ","FullName":"БУЗ УР \"ЮКАМЕНСКАЯ РБ МЗ УР\"","NameBash":"","NameLuk":"Регионсбыт ЮЦРБ"},{"Name":"Юкаменский совет депутатов","FullName":"СОВЕТ ДЕПУТАТОВ МУНИЦИПАЛЬНОГО ОБРАЗОВАНИЯ \"ЮКАМЕНСКИЙ РАЙОН\"","NameBash":"","NameLuk":"Регионсбыт ЮСДеп"},{"Name":"Юскинская школа Кез","FullName":"МКОУ \"ЮСКИНСКАЯ СОШ\"","NameBash":"Регионсбыт 25","NameLuk":"Юськинская СОШ"},{"Name":"Якшур-Бодинская ДЮСШ","FullName":"МБОУ ДОД ЯКШУР-БОДЬИНСКАЯ ДЮСШ","NameBash":"Регионсбыт 66","NameLuk":""},{"Name":"ЯРСКАЯ ЦРБ ","FullName":"БУЗ УР \"ЯРСКАЯ РБ МЗ УР\"","NameBash":"Регионсбыт 46","NameLuk":"Регионсбыт Я ЦРБ"}]
